testflocken/__init__.py
testflocken/__main__.py
testflocken/app.py
testflocken/cli.py
testflocken/py.typed
testflocken-1.0.1.dist-info/METADATA
testflocken-1.0.1.dist-info/WHEEL
testflocken-1.0.1.dist-info/entry_points.txt
testflocken-1.0.1.dist-info/RECORD
